sphinx_reports/CodeCoverage.py
sphinx_reports/Common.py
sphinx_reports/Dependency.py
sphinx_reports/DocCoverage.py
sphinx_reports/Sphinx.py
sphinx_reports/Unittest.py
sphinx_reports/__init__.py
sphinx_reports/py.typed
sphinx_reports/Adapter/Coverage.py
sphinx_reports/Adapter/Dependency.py
sphinx_reports/Adapter/__init__.py
sphinx_reports/DataModel/CodeCoverage.py
sphinx_reports/DataModel/Dependency.py
sphinx_reports/DataModel/__init__.py
sphinx_reports/static/__init__.py
sphinx_reports/static/sphinx-reports.css
sphinx_reports-0.10.0.dist-info/licenses/LICENSE.md
sphinx_reports-0.10.0.dist-info/METADATA
sphinx_reports-0.10.0.dist-info/WHEEL
sphinx_reports-0.10.0.dist-info/top_level.txt
sphinx_reports-0.10.0.dist-info/RECORD
