Metadata-Version: 2.4
Name: sphinx_reports
Version: 0.10.0
Summary: A Sphinx extension providing reports and summaries embedded in documentation pages.
Home-page: https://GitHub.com/pyTooling/sphinx_reports
Author: Patrick Lehmann
Author-email: Paebbels@gmail.com
License: Apache-2.0
Project-URL: Documentation, https://pyTooling.GitHub.io/sphinx_reports
Project-URL: Source Code, https://GitHub.com/pyTooling/sphinx_reports
Project-URL: Issue Tracker, https://GitHub.com/pyTooling/sphinx_reports/issues
Keywords: Python3,Sphinx,Extension,Report,doc-string,interrogate,Code Coverage,Coverage,Documentation Coverage,Unittest,Dependencies,Summary
Classifier: Operating System :: OS Independent
Classifier: Intended Audience :: Developers
Classifier: Topic :: Utilities
Classifier: Framework :: Sphinx
Classifier: Framework :: Sphinx :: Domain
Classifier: Framework :: Sphinx :: Extension
Classifier: Topic :: Documentation :: Sphinx
Classifier: Topic :: Software Development :: Documentation
Classifier: Topic :: Software Development :: Quality Assurance
Classifier: Topic :: Software Development :: Testing :: Unit
Classifier: License :: OSI Approved :: Apache Software License
Classifier: Programming Language :: Python :: 3 :: Only
Classifier: Programming Language :: Python :: 3.11
Classifier: Programming Language :: Python :: 3.12
Classifier: Programming Language :: Python :: 3.13
Classifier: Programming Language :: Python :: 3.14
Classifier: Development Status :: 4 - Beta
Requires-Python: >=3.11
License-File: LICENSE.md
Requires-Dist: Coverage~=7.13
Requires-Dist: sphinx<10.0,>=9.0
Requires-Dist: docutils>=0.22.0
Requires-Dist: docstr_coverage~=2.3.2
Requires-Dist: pyEDAA.Reports~=0.17.0
Requires-Dist: pyTooling>=8.0
Requires-Dist: docutils_stubs>=0.0.22
Provides-Extra: doc
Requires-Dist: sphinx-copybutton~=0.5.0; extra == "doc"
Requires-Dist: autoapi~=2.0.1; extra == "doc"
Requires-Dist: Coverage~=7.13; extra == "doc"
Requires-Dist: sphinx_autodoc_typehints~=3.6; extra == "doc"
Requires-Dist: sphinx<10.0,>=9.0; extra == "doc"
Requires-Dist: docutils>=0.22.0; extra == "doc"
Requires-Dist: docstr_coverage~=2.3.2; extra == "doc"
Requires-Dist: pyEDAA.Reports~=0.17.0; extra == "doc"
Requires-Dist: pyTooling>=8.0; extra == "doc"
Requires-Dist: sphinxcontrib-mermaid~=2.0; extra == "doc"
Requires-Dist: sphinx_rtd_theme~=3.1; extra == "doc"
Requires-Dist: docutils_stubs>=0.0.22; extra == "doc"
Requires-Dist: sphinx_design~=0.7.0; extra == "doc"
Provides-Extra: test
Requires-Dist: pytest~=9.0; extra == "test"
Requires-Dist: pytest-cov~=7.0; extra == "test"
Requires-Dist: lxml<7.0,>=5.4; extra == "test"
Requires-Dist: Coverage~=7.13; extra == "test"
Requires-Dist: sphinx<10.0,>=9.0; extra == "test"
Requires-Dist: docutils>=0.22.0; extra == "test"
Requires-Dist: docstr_coverage~=2.3.2; extra == "test"
Requires-Dist: pyEDAA.Reports~=0.17.0; extra == "test"
Requires-Dist: typing_extensions~=4.15; extra == "test"
Requires-Dist: pyTooling>=8.0; extra == "test"
Requires-Dist: docutils_stubs>=0.0.22; extra == "test"
Requires-Dist: mypy[reports]~=1.19; extra == "test"
Provides-Extra: all
Requires-Dist: pytest~=9.0; extra == "all"
Requires-Dist: pytest-cov~=7.0; extra == "all"
Requires-Dist: autoapi~=2.0.1; extra == "all"
Requires-Dist: sphinx_rtd_theme~=3.1; extra == "all"
Requires-Dist: Coverage~=7.13; extra == "all"
Requires-Dist: sphinx_autodoc_typehints~=3.6; extra == "all"
Requires-Dist: sphinx<10.0,>=9.0; extra == "all"
Requires-Dist: docutils>=0.22.0; extra == "all"
Requires-Dist: docstr_coverage~=2.3.2; extra == "all"
Requires-Dist: pyEDAA.Reports~=0.17.0; extra == "all"
Requires-Dist: docutils_stubs>=0.0.22; extra == "all"
Requires-Dist: pyTooling>=8.0; extra == "all"
Requires-Dist: lxml<7.0,>=5.4; extra == "all"
Requires-Dist: typing_extensions~=4.15; extra == "all"
Requires-Dist: sphinx-copybutton~=0.5.0; extra == "all"
Requires-Dist: sphinxcontrib-mermaid~=2.0; extra == "all"
Requires-Dist: sphinx_design~=0.7.0; extra == "all"
Requires-Dist: mypy[reports]~=1.19; extra == "all"
Dynamic: author
Dynamic: author-email
Dynamic: classifier
Dynamic: description
Dynamic: description-content-type
Dynamic: home-page
Dynamic: keywords
Dynamic: license
Dynamic: license-file
Dynamic: project-url
Dynamic: provides-extra
Dynamic: requires-dist
Dynamic: requires-python
Dynamic: summary
